setup.py
metlog_raven/__init__.py
metlog_raven/raven_plugin.py
metlog_raven.egg-info/PKG-INFO
metlog_raven.egg-info/SOURCES.txt
metlog_raven.egg-info/dependency_links.txt
metlog_raven.egg-info/not-zip-safe
metlog_raven.egg-info/requires.txt
metlog_raven.egg-info/top_level.txt