Metadata-Version: 1.0
Name: metlog-raven
Version: 0.2
Summary: A Metlog plugin to send exceptions to Sentry
Home-page: http://github.com/mozilla-services/metlog-raven
Author: Victor Ng
Author-email: vng@mozilla.com
License: MPLv2.0
Platform: UNKNOWN
Classifier: License :: OSI Approved :: Mozilla Public License 2.0 (MPL 2.0)
